{
  "name": "Delete a repository invitation",
  "enabledForApps": true,
  "method": "DELETE",
  "path": "/repos/:owner/:repo/invitations/:invitation_id",
  "params": [
    {
      "name": "owner",
      "type": "string",
      "required": true,
      "description": "",
      "location": "path"
    },
    {
      "name": "repo",
      "type": "string",
      "required": true,
      "description": "",
      "location": "path"
    },
    {
      "name": "invitation_id",
      "type": "string",
      "required": true,
      "description": "",
      "location": "path"
    }
  ],
  "description": "",
  "documentationUrl": "https://developer.github.com/v3/repos/invitations/#delete-a-repository-invitation"
}
