{
  "name": "Update LDAP mapping for a team",
  "enabledForApps": false,
  "method": "PATCH",
  "path": "/admin/ldap/teams/:team_id/mapping",
  "previews": [
    {
      "name": "hellcat",
      "description": "**Note:** The Nested Teams API is currently available for developers to preview. See the [blog post](https://developer.github.com/changes/2017-08-30-preview-nested-teams) for full details. To access the API, you must provide a custom [media type](https://developer.github.com/enterprise/2.17/v3/media) in the `Accept` header:\n\n```\napplication/vnd.github.hellcat-preview+json\n\n```",
      "required": false
    }
  ],
  "params": [
    {
      "name": "team_id",
      "type": "integer",
      "required": true,
      "description": "",
      "location": "url"
    },
    {
      "name": "ldap_dn",
      "type": "string",
      "description": "The [distinguished name](https://www.ldap.com/ldap-dns-and-rdns) (DN) of the LDAP entry to map to a team.",
      "required": false,
      "location": "body"
    }
  ],
  "requests": [
    {
      "ldap_dn": "cn=Enterprise Ops,ou=teams,dc=github,dc=com"
    }
  ],
  "description": "Updates the [distinguished name](https://www.ldap.com/ldap-dns-and-rdns) (DN) of the LDAP entry to map to a team. [LDAP synchronization](https://help.github.com/enterprise/admin/guides/user-management/using-ldap/#enabling-ldap-sync) must be enabled to map LDAP entries to a team. Use the [Create team](https://developer.github.com/enterprise/2.17/v3/teams/#create-team) endpoint to create a team with LDAP mapping.\n\nIf you pass the `hellcat-preview` media type, you can also update the LDAP mapping of a child team.",
  "responses": [
    {
      "headers": {
        "status": "200 OK",
        "content-type": "application/json; charset=utf-8"
      },
      "body": {
        "ldap_dn": "cn=Enterprise Ops,ou=teams,dc=github,dc=com",
        "id": 1,
        "node_id": "MDQ6VGVhbTE=",
        "url": "https://api.github.com/teams/1",
        "name": "Justice League",
        "slug": "justice-league",
        "description": "A great team.",
        "privacy": "closed",
        "permission": "admin",
        "members_url": "https://api.github.com/teams/1/members{/member}",
        "repositories_url": "https://api.github.com/teams/1/repos",
        "parent": null
      }
    }
  ],
  "idName": "update-ldap-mapping-for-team",
  "documentationUrl": "https://developer.github.com/enterprise/2.17/v3/enterprise-admin/ldap/#update-ldap-mapping-for-a-team"
}
