{
  "name": "List comments in a repository",
  "enabledForApps": true,
  "method": "GET",
  "path": "/repos/:owner/:repo/issues/comments",
  "params": [
    {
      "name": "sort",
      "type": "enum",
      "options": [
        "created",
        "updated"
      ],
      "description": "Either `created` or `updated`.",
      "default": "created",
      "required": false
    },
    {
      "name": "direction",
      "type": "enum",
      "options": [
        "asc",
        "desc",
        "sort"
      ],
      "description": "Either `asc` or `desc`. Ignored without the `sort` parameter.",
      "required": false
    },
    {
      "name": "since",
      "type": "string",
      "description": "Only comments updated at or after this time are returned. This is a timestamp in ISO 8601 format: `YYYY-MM-DDTHH:MM:SSZ`.",
      "required": false
    }
  ],
  "description": "By default, Issue Comments are ordered by ascending ID.",
  "documentationUrl": "https://developer.github.com/v3/issues/comments/#list-comments-in-a-repository"
}
