{
  "name": "Remove user restrictions of protected branch",
  "enabledForApps": true,
  "method": "DELETE",
  "path": "/repos/:owner/:repo/branches/:branch/protection/restrictions/users",
  "params": [
    {
      "name": "owner",
      "type": "string",
      "required": true,
      "description": "",
      "location": "url"
    },
    {
      "name": "repo",
      "type": "string",
      "required": true,
      "description": "",
      "location": "url"
    },
    {
      "name": "branch",
      "type": "string",
      "required": true,
      "description": "",
      "location": "url"
    }
  ],
  "description": "Removes the ability of a team to push to this branch.\n\n| Type    | Description                                                                                                                            |\n| ------- | -------------------------------------------------------------------------------------------------------------------------------------- |\n| `array` | Usernames of the people who should no longer have push access. **Note**: The list of users and teams in total is limited to 100 items. |",
  "idName": "remove-protected-branch-user-restrictions",
  "documentationUrl": "https://developer.github.com/v3/repos/branches/#remove-user-restrictions-of-protected-branch"
}
