[
  {
    "name": "List outside collaborators",
    "method": "GET",
    "path": "/orgs/:org/outside_collaborators",
    "description": "List all users who are outside collaborators of an organization.",
    "params": [
      {
        "name": "filter",
        "type": "string",
        "description": "Filter the list of outside collaborators. Can be one of:  \n\\* `2fa_disabled`: Outside collaborators without [two-factor authentication](https://github.com/blog/1614-two-factor-authentication) enabled.  \n\\* `all`: All outside collaborators.  \n  \nDefault: `all`"
      }
    ],
    "documentationUrl": "https://developer.github.com/v3/orgs/outside_collaborators/#list-outside-collaborators"
  },
  {
    "name": "Remove outside collaborator",
    "method": "DELETE",
    "path": "/orgs/:org/outside_collaborators/:username",
    "description": "Removing a user from this list will remove them from all the organization's repositories.",
    "params": [],
    "documentationUrl": "https://developer.github.com/v3/orgs/outside_collaborators/#remove-outside-collaborator"
  },
  {
    "name": "Convert member to outside collaborator",
    "method": "PUT",
    "path": "/orgs/:org/outside_collaborators/:username",
    "description": "When an organization member is converted to an outside collaborator, they'll only have access to the repositories that their current team membership allows. The user will no longer be a member of the organization. For more information, see \"[Converting an organization member to an outside collaborator](https://help.github.com/articles/converting-an-organization-member-to-an-outside-collaborator/)\".",
    "params": [],
    "documentationUrl": "https://developer.github.com/v3/orgs/outside_collaborators/#convert-member-to-outside-collaborator"
  }
]