{
  "name": "Get single global hook",
  "enabledForApps": false,
  "method": "GET",
  "path": "/admin/hooks/:hook_id",
  "previews": [
    {
      "name": "superpro",
      "description": "**Note:** The [Global Webhooks API](https://developer.github.com/enterprise/2.15/v3/enterprise-admin/global_webhooks/) is currently available for developers to preview. To access the API during the preview period, you must provide a custom [media type](https://developer.github.com/enterprise/2.15/v3/media) in the `Accept` header:\n\n```\napplication/vnd.github.superpro-preview+json\n\n```",
      "required": true
    }
  ],
  "params": [
    {
      "name": "hook_id",
      "type": "integer",
      "required": true,
      "description": "",
      "location": "url"
    }
  ],
  "description": "",
  "responses": [
    {
      "headers": {
        "status": "200 OK",
        "content-type": "application/json; charset=utf-8"
      },
      "body": {
        "type": "Global",
        "id": 1,
        "name": "web",
        "active": true,
        "events": [
          "organization",
          "user"
        ],
        "config": {
          "url": "https://example.com",
          "content_type": "json",
          "insecure_ssl": "0",
          "secret": "********"
        },
        "updated_at": "2017-12-07T00:14:59Z",
        "created_at": "2017-12-07T00:14:59Z",
        "url": "https://api.github.com/admin/hooks/1",
        "ping_url": "https://api.github.com/admin/hooks/1/pings"
      }
    }
  ],
  "idName": "get-global-hook",
  "documentationUrl": "https://developer.github.com/enterprise/2.15/v3/enterprise-admin/global_webhooks/#get-single-global-hook"
}
