{
  "name": "Get an organization",
  "enabledForApps": true,
  "method": "GET",
  "path": "/orgs/:org",
  "params": [
    {
      "name": "org",
      "type": "string",
      "required": true,
      "description": "",
      "location": "url"
    }
  ],
  "description": "To see many of the organization response values, you need to be an authenticated organization owner with the `admin:org` scope. When the value of `two_factor_requirement_enabled` is `true`, the organization requires all members, billing managers, and outside collaborators to enable [two-factor authentication](https://help.github.com/articles/securing-your-account-with-two-factor-authentication-2fa/).",
  "idName": "get",
  "documentationUrl": "https://developer.github.com/v3/orgs/#get-an-organization"
}
