{
  "name": "Get a specific Pages build",
  "enabledForApps": true,
  "method": "GET",
  "path": "/repos/:owner/:repo/pages/builds/:build_id",
  "previews": [],
  "params": [
    {
      "name": "owner",
      "type": "string",
      "required": true,
      "description": "",
      "location": "url"
    },
    {
      "name": "repo",
      "type": "string",
      "required": true,
      "description": "",
      "location": "url"
    },
    {
      "name": "build_id",
      "type": "integer",
      "required": true,
      "description": "",
      "location": "url"
    }
  ],
  "description": "",
  "idName": "get-pages-build",
  "documentationUrl": "https://developer.github.com/enterprise/2.14/v3/repos/pages/#get-a-specific-pages-build"
}
