{
  "name": "List teams",
  "enabledForApps": true,
  "method": "GET",
  "path": "/repos/:owner/:repo/teams",
  "params": [
    {
      "name": "owner",
      "type": "string",
      "required": true,
      "description": ""
    },
    {
      "name": "repo",
      "type": "string",
      "required": true,
      "description": ""
    },
    {
      "name": "per_page",
      "type": "number",
      "required": false,
      "description": "Results per page (max 100)",
      "default": 30
    },
    {
      "name": "page",
      "type": "number",
      "required": false,
      "description": "Page number of the results to fetch.",
      "default": 1
    }
  ],
  "description": "",
  "documentationUrl": "https://developer.github.com/v3/repos/#list-teams"
}
