{
  "name": "Delete an impersonation OAuth token",
  "enabledForApps": false,
  "method": "DELETE",
  "path": "/admin/users/:username/authorizations",
  "previews": [],
  "params": [
    {
      "name": "username",
      "type": "string",
      "required": true,
      "description": "",
      "location": "url"
    }
  ],
  "description": "",
  "responses": [
    {
      "headers": {
        "status": "204 No Content",
        "content-type": "application/json; charset=utf-8"
      }
    }
  ],
  "idName": "delete-impersonation-o-auth-token",
  "documentationUrl": "https://developer.github.com/enterprise/2.16/v3/enterprise-admin/users/#delete-an-impersonation-oauth-token"
}
