{
  "summary": "Check if a user is a collaborator",
  "description": "For organization-owned repositories, the list of collaborators includes outside collaborators, organization members that are direct collaborators, organization members with access through team memberships, organization members with access through default organization permissions, and organization owners.\n\nIf you pass the `hellcat-preview` media type, team members will include the members of child teams.",
  "operationId": "repos/check-collaborator",
  "tags": ["repos"],
  "externalDocs": {
    "description": "API method documentation",
    "url": "https://developer.github.com/enterprise/2.18/v3/repos/collaborators/#check-if-a-user-is-a-collaborator"
  },
  "parameters": [
    {
      "name": "accept",
      "description": "Setting to `application/vnd.github.v3+json` is recommended",
      "in": "header",
      "schema": {
        "type": "string",
        "default": "application/vnd.github.v3+json"
      }
    },
    {
      "name": "owner",
      "description": "owner parameter",
      "in": "path",
      "required": true,
      "schema": { "type": "string" }
    },
    {
      "name": "repo",
      "description": "repo parameter",
      "in": "path",
      "required": true,
      "schema": { "type": "string" }
    },
    {
      "name": "username",
      "description": "username parameter",
      "in": "path",
      "required": true,
      "schema": { "type": "string" }
    }
  ],
  "responses": {
    "204": { "description": "Response if user is a collaborator" },
    "404": { "description": "Response if user is not a collaborator" }
  },
  "x-code-samples": [
    {
      "lang": "Shell",
      "source": "curl \\\n  -H\"Accept: application/vnd.github.v3+json\" \\\n  http://{hostname}/repos/octocat/hello-world/collaborators/USERNAME"
    },
    {
      "lang": "JS",
      "source": "octokit.repos.checkCollaborator({\n  owner: 'octocat',\n  repo: 'hello-world',\n  username: 'username'\n})"
    }
  ],
  "x-github": {
    "legacy": false,
    "enabledForApps": true,
    "githubCloudOnly": false,
    "previews": [
      {
        "name": "hellcat",
        "note": "**Note:** The Nested Teams API is currently available for developers to preview. See the [blog post](https://developer.github.com/changes/2017-08-30-preview-nested-teams) for full details. To access the API, you must provide a custom [media type](https://developer.github.com/enterprise/2.18/v3/media) in the `Accept` header:\n\n```\napplication/vnd.github.hellcat-preview+json\n\n```",
        "required": false
      }
    ]
  },
  "x-changes": []
}
