[
  {
    "id": "metadata-permissions",
    "name": "Metadata permissions",
    "url": "https://developer.github.com/enterprise/2.14/v3/apps/permissions/#metadata-permissions"
  },
  {
    "id": "permission-on-administration",
    "name": "Permission on \"administration\"",
    "url": "https://developer.github.com/enterprise/2.14/v3/apps/permissions/#permission-on-administration"
  },
  {
    "id": "permission-on-checks",
    "name": "Permission on \"checks\"",
    "url": "https://developer.github.com/enterprise/2.14/v3/apps/permissions/#permission-on-checks"
  },
  {
    "id": "permission-on-contents",
    "name": "Permission on \"contents\"",
    "url": "https://developer.github.com/enterprise/2.14/v3/apps/permissions/#permission-on-contents"
  },
  {
    "id": "permission-on-deployments",
    "name": "Permission on \"deployments\"",
    "url": "https://developer.github.com/enterprise/2.14/v3/apps/permissions/#permission-on-deployments"
  },
  {
    "id": "permission-on-emails",
    "name": "Permission on \"emails\"",
    "url": "https://developer.github.com/enterprise/2.14/v3/apps/permissions/#permission-on-emails"
  },
  {
    "id": "permission-on-followers",
    "name": "Permission on \"followers\"",
    "url": "https://developer.github.com/enterprise/2.14/v3/apps/permissions/#permission-on-followers"
  },
  {
    "id": "permission-on-gpg-keys",
    "name": "Permission on \"gpg keys\"",
    "url": "https://developer.github.com/enterprise/2.14/v3/apps/permissions/#permission-on-gpg-keys"
  },
  {
    "id": "permission-on-issues",
    "name": "Permission on \"issues\"",
    "url": "https://developer.github.com/enterprise/2.14/v3/apps/permissions/#permission-on-issues"
  },
  {
    "id": "permission-on-keys",
    "name": "Permission on \"keys\"",
    "url": "https://developer.github.com/enterprise/2.14/v3/apps/permissions/#permission-on-keys"
  },
  {
    "id": "permission-on-members",
    "name": "Permission on \"members\"",
    "url": "https://developer.github.com/enterprise/2.14/v3/apps/permissions/#permission-on-members"
  },
  {
    "id": "permission-on-organization-administration",
    "name": "Permission on \"organization administration\"",
    "url": "https://developer.github.com/enterprise/2.14/v3/apps/permissions/#permission-on-organization-administration"
  },
  {
    "id": "permission-on-organization-hooks",
    "name": "Permission on \"organization hooks\"",
    "url": "https://developer.github.com/enterprise/2.14/v3/apps/permissions/#permission-on-organization-hooks"
  },
  {
    "id": "permission-on-organization-projects",
    "name": "Permission on \"organization projects\"",
    "url": "https://developer.github.com/enterprise/2.14/v3/apps/permissions/#permission-on-organization-projects"
  },
  {
    "id": "permission-on-packages",
    "name": "Permission on \"packages\"",
    "url": "https://developer.github.com/enterprise/2.14/v3/apps/permissions/#permission-on-packages"
  },
  {
    "id": "permission-on-pages",
    "name": "Permission on \"pages\"",
    "url": "https://developer.github.com/enterprise/2.14/v3/apps/permissions/#permission-on-pages"
  },
  {
    "id": "permission-on-pull-requests",
    "name": "Permission on \"pull requests\"",
    "url": "https://developer.github.com/enterprise/2.14/v3/apps/permissions/#permission-on-pull-requests"
  },
  {
    "id": "permission-on-repository-hooks",
    "name": "Permission on \"repository hooks\"",
    "url": "https://developer.github.com/enterprise/2.14/v3/apps/permissions/#permission-on-repository-hooks"
  },
  {
    "id": "permission-on-repository-projects",
    "name": "Permission on \"repository projects\"",
    "url": "https://developer.github.com/enterprise/2.14/v3/apps/permissions/#permission-on-repository-projects"
  },
  {
    "id": "permission-on-single-file",
    "name": "Permission on \"single file\"",
    "url": "https://developer.github.com/enterprise/2.14/v3/apps/permissions/#permission-on-single-file"
  },
  {
    "id": "permission-on-starring",
    "name": "Permission on \"starring\"",
    "url": "https://developer.github.com/enterprise/2.14/v3/apps/permissions/#permission-on-starring"
  },
  {
    "id": "permission-on-statuses",
    "name": "Permission on \"statuses\"",
    "url": "https://developer.github.com/enterprise/2.14/v3/apps/permissions/#permission-on-statuses"
  },
  {
    "id": "permission-on-team-discussions",
    "name": "Permission on \"team discussions\"",
    "url": "https://developer.github.com/enterprise/2.14/v3/apps/permissions/#permission-on-team-discussions"
  }
]
