{
  "name": "Delete a pending review",
  "enabledForApps": true,
  "method": "DELETE",
  "path": "/repos/:owner/:repo/pulls/:number/reviews/:id",
  "params": [
    {
      "name": "owner",
      "type": "string",
      "required": true,
      "description": "",
      "location": "url"
    },
    {
      "name": "repo",
      "type": "string",
      "required": true,
      "description": "",
      "location": "url"
    },
    {
      "name": "number",
      "type": "integer",
      "required": true,
      "description": "",
      "location": "url"
    },
    {
      "name": "id",
      "type": "string",
      "required": true,
      "description": "",
      "location": "url"
    }
  ],
  "description": "",
  "idName": "delete-pending-review",
  "documentationUrl": "https://developer.github.com/v3/pulls/reviews/#delete-a-pending-review"
}
