{
  "summary": "Delete a repository invitation",
  "description": "",
  "operationId": "repos/delete-invitation",
  "tags": ["repos"],
  "externalDocs": {
    "description": "API method documentation",
    "url": "https://developer.github.com/enterprise/2.20/v3/repos/invitations/#delete-a-repository-invitation"
  },
  "parameters": [
    {
      "name": "accept",
      "description": "Setting to `application/vnd.github.v3+json` is recommended",
      "in": "header",
      "schema": {
        "type": "string",
        "default": "application/vnd.github.v3+json"
      }
    },
    {
      "name": "owner",
      "in": "path",
      "required": true,
      "schema": { "type": "string" }
    },
    {
      "name": "repo",
      "in": "path",
      "required": true,
      "schema": { "type": "string" }
    },
    {
      "name": "invitation_id",
      "in": "path",
      "required": true,
      "schema": { "type": "integer" }
    }
  ],
  "responses": { "204": { "description": "Empty response" } },
  "x-code-samples": [
    {
      "lang": "Shell",
      "source": "curl \\\n  -XDELETE \\\n  -H\"Accept: application/vnd.github.v3+json\" \\\n  http://{hostname}/repos/octocat/hello-world/invitations/42"
    },
    {
      "lang": "JS",
      "source": "octokit.repos.deleteInvitation({\n  owner: 'octocat',\n  repo: 'hello-world',\n  invitation_id: 42\n})"
    },
    {
      "lang": "Ruby",
      "source": "octokit.delete_invitation(\n  'hello-world',\n  42\n)"
    }
  ],
  "x-github": {
    "legacy": false,
    "enabledForApps": true,
    "githubCloudOnly": false,
    "previews": []
  },
  "x-changes": []
}
